osirisvalidator/__init__.py
osirisvalidator/exceptions.py
osirisvalidator/internet.py
osirisvalidator/number.py
osirisvalidator/osiris.py
osirisvalidator/string.py
osirisvalidator/intl/__init__.py
osirisvalidator/intl/br.py
osirisvalidator/locale/pt_BR/LC_MESSAGES/osiris.po
osirisvalidator/tests/__init__.py
osirisvalidator/tests/test_internet.py
osirisvalidator/tests/test_number.py
osirisvalidator/tests/test_string.py
osirisvalidator/tests/intl/__init__.py
osirisvalidator/tests/intl/test_br.py
osirisvalidator-0.1.2.dist-info/LICENSE
osirisvalidator-0.1.2.dist-info/METADATA
osirisvalidator-0.1.2.dist-info/WHEEL
osirisvalidator-0.1.2.dist-info/top_level.txt
osirisvalidator-0.1.2.dist-info/RECORD
