Metadata-Version: 2.1
Name: osirisvalidator
Version: 0.1.2
Summary: Validators for fields in Flask-Restless
Home-page: https://github.com/davidaug/osirisvalidator
Author: David Veiga
Author-email: david@david.blog.br
License: UNKNOWN
Platform: UNKNOWN
Classifier: Development Status :: 3 - Alpha
Classifier: Programming Language :: Python :: 3
Classifier: License :: OSI Approved :: GNU General Public License v3 (GPLv3)
Classifier: Operating System :: OS Independent
Classifier: Topic :: Software Development :: Libraries :: Python Modules
Requires-Python: >=3.6
